MANIFEST.in
README.rst
bootstrap.py
buildout.cfg
setup.py
demo/grappelli/__init__.py
demo/grappelli/models.py
demo/grappelli/settings.py
demo/grappelli/urls.py
demo/grappelli/dashboard/__init__.py
demo/grappelli/dashboard/dashboards.py
demo/grappelli/dashboard/modules.py
demo/grappelli/dashboard/registry.py
demo/grappelli/dashboard/utils.py
demo/grappelli/dashboard/management/__init__.py
demo/grappelli/dashboard/management/commands/__init__.py
demo/grappelli/dashboard/management/commands/customdashboard.py
demo/grappelli/dashboard/templatetags/__init__.py
demo/grappelli/dashboard/templatetags/grp_dashboard_tags.py
demo/grappelli/templatetags/__init__.py
demo/grappelli/templatetags/grp_tags.py
demo/grappelli/views/__init__.py
demo/grappelli/views/related.py
gnowsys_studio.egg-info/PKG-INFO
gnowsys_studio.egg-info/SOURCES.txt
gnowsys_studio.egg-info/dependency_links.txt
gnowsys_studio.egg-info/not-zip-safe
gnowsys_studio.egg-info/requires.txt
gnowsys_studio.egg-info/top_level.txt
gstudio/__init__.py
gstudio/comparison.py
gstudio/context_processors.py
gstudio/feeds.py
gstudio/forms.py
gstudio/gnowql.py
gstudio/managers.py
gstudio/models.py
gstudio/moderator.py
gstudio/ping.py
gstudio/rdf.py
gstudio/regbackend.py
gstudio/search.py
gstudio/settings.py
gstudio/signals.py
gstudio/sitemaps.py
gstudio/testloop.py
gstudio/testsettings.py
gstudio/admin/__init__.py
gstudio/admin/attribute.py
gstudio/admin/attribute_bigintegerfield.py
gstudio/admin/attribute_booleanfield.py
gstudio/admin/attribute_charfield.py
gstudio/admin/attribute_commaseparatedintegerfield.py
gstudio/admin/attribute_datefield.py
gstudio/admin/attribute_datetimefield.py
gstudio/admin/attribute_decimalfield.py
gstudio/admin/attribute_emailfield.py
gstudio/admin/attribute_filefield.py
gstudio/admin/attribute_filepathfield.py
gstudio/admin/attribute_floatfield.py
gstudio/admin/attribute_imagefield.py
gstudio/admin/attribute_integerfield.py
gstudio/admin/attribute_ipaddressfield.py
gstudio/admin/attribute_nullbooleanfield.py
gstudio/admin/attribute_positiveintegerfield.py
gstudio/admin/attribute_textfield.py
gstudio/admin/attribute_timefield.py
gstudio/admin/attribute_urlfield.py
gstudio/admin/attributespecification.py
