Metadata-Version: 1.0
Name: gnowsys-studio
Version: 0.4.dev
Summary: A collaborative blogspace for constructing and publishing semantic knowledge networks and ontologies
Home-page: http://github.com/gnowgi/django-gstudio
Author: Nagarjuna G
Author-email: nagarjun@gnowledge.org
License: AGPLv3
Keywords: django,blog,post,news,gnowsys,gnowledge,semantic,networks,ontolgies,concept map,concept graph
Platform: UNKNOWN
Classifier: Framework :: Django
Classifier: Development Status :: 3 - Alpha
Classifier: Environment :: Web Environment
Classifier: Programming Language :: Python
Classifier: Intended Audience :: Developers
Classifier: Operating System :: OS Independent
Classifier: License :: OSI Approved :: GNU Affero General Public License v3
Classifier: Topic :: Scientific/Engineering :: Artificial Intelligence
Classifier: Topic :: Scientific/Engineering :: Information Analysis
Classifier: Topic :: Scientific/Engineering :: Visualization
